presidiopy/__init__.py
presidiopy2-0.0.2.dist-info/LICENSE
presidiopy2-0.0.2.dist-info/METADATA
presidiopy2-0.0.2.dist-info/WHEEL
presidiopy2-0.0.2.dist-info/top_level.txt
presidiopy2-0.0.2.dist-info/RECORD
