Metadata-Version: 2.1
Name: presidiopy2
Version: 0.0.2
Summary: An API library to interact with Microsoft Presidio
Home-page: https://github.com/querylayer/presidiopy
Author: David Hernandez
Author-email: hello@davidhernandez.info
License: UNKNOWN
Project-URL: Bug Tracker, https://github.com/querylayer/presidiopy/issues
Project-URL: Source Code, https://github.com/querylayer/presidiopy
Platform: UNKNOWN
Classifier: Programming Language :: Python :: 3
Classifier: License :: OSI Approved :: GNU General Public License v3 (GPLv3)
Classifier: Operating System :: OS Independent
Requires-Python: >=3.6
Requires-Dist: requests (>=2.22.0)
